diffractsim/__init__.py
diffractsim/colour_functions.py
diffractsim/monochromatic_simulator.py
diffractsim/polychromatic_simulator.py
diffractsim/data/LED_6770K.txt
diffractsim/data/ceramic_metal_halide.txt
diffractsim/data/cie-cmf.txt
diffractsim/data/compact_fluorescent_lamp.txt
diffractsim/data/high_pressure_sodium.txt
diffractsim/data/illuminant_d65.txt
diffractsim/data/incandescent_tugsten.txt
diffractsim/data/mercury_vapor.txt
diffractsim/diffractive_elements/SLM.py
diffractsim/diffractive_elements/__init__.py
diffractsim/diffractive_elements/aperture_from_function.py
diffractsim/diffractive_elements/aperture_from_image.py
diffractsim/diffractive_elements/axicon.py
diffractsim/diffractive_elements/circular_aperture.py
diffractsim/diffractive_elements/diffractive_element.py
diffractsim/diffractive_elements/fresnel_zone_plate.py
diffractsim/diffractive_elements/grating.py
diffractsim/diffractive_elements/hexagonal_aperture.py
diffractsim/diffractive_elements/lens.py
diffractsim/diffractive_elements/rectangular_slit.py
diffractsim/holography/__init__.py
diffractsim/holography/custom_phase_retrieval.py
diffractsim/holography/fourier_phase_retrieval.py
diffractsim/holography/rotational_symmetric_phase_design.py
diffractsim/light_sources/__init__.py
diffractsim/light_sources/gaussian_beam.py
diffractsim/light_sources/light_source.py
diffractsim/light_sources/plane_wave.py
diffractsim/light_sources/spatial_noise.py
diffractsim/polynomials/__init__.py
diffractsim/polynomials/hermite_gaussian_modes.py
diffractsim/polynomials/laguerre_gaussian_modes.py
diffractsim/polynomials/zernike_polynomials.py
diffractsim/propagation_methods/PSF_convolution.py
diffractsim/propagation_methods/__init__.py
diffractsim/propagation_methods/angular_spectrum_method.py
diffractsim/propagation_methods/bluestein_method.py
diffractsim/propagation_methods/two_steps_fresnel_method.py
diffractsim/util/__init__.py
diffractsim/util/backend_functions.py
diffractsim/util/bluestein_FFT.py
diffractsim-2.2.13.dist-info/licenses/LICENSE
diffractsim-2.2.13.dist-info/METADATA
diffractsim-2.2.13.dist-info/WHEEL
diffractsim-2.2.13.dist-info/top_level.txt
diffractsim-2.2.13.dist-info/RECORD
