Metadata-Version: 2.4
Name: diffractsim
Version: 2.2.13
Summary: A flexible diffraction simulator for exploring and visualizing physical optics
Home-page: https://github.com/rafael-fuente/Diffraction-Simulations--Angular-Spectrum-Method
Download-URL: https://github.com/rafael-fuente/Diffraction-Simulations--Angular-Spectrum-Method/archive/main.zip
Author: Rafael de la Fuente
Author-email: rafael.fuente.herrezuelo@gmail.com
License: MPL 2.0
Keywords: diffraction,angular spectrum method,optics,physics simulation
Classifier: Development Status :: 5 - Production/Stable
Classifier: Intended Audience :: Science/Research
Classifier: Topic :: Scientific/Engineering
Classifier: License :: OSI Approved :: BSD License
Classifier: Operating System :: OS Independent
Requires-Python: >=3.6
License-File: LICENSE
Requires-Dist: numpy
Requires-Dist: scipy
Requires-Dist: Pillow
Requires-Dist: matplotlib
Requires-Dist: progressbar
Requires-Dist: jax
Dynamic: author
Dynamic: author-email
Dynamic: classifier
Dynamic: description
Dynamic: description-content-type
Dynamic: download-url
Dynamic: home-page
Dynamic: keywords
Dynamic: license
Dynamic: license-file
Dynamic: requires-dist
Dynamic: requires-python
Dynamic: summary
